{"reason":"Push on VFS changes","startTime":"2023-10-09T16:56:54.410042171+01:00[Europe/Lisbon]","duration":274064,"isCancelled":false}
{"reason":"Push on VFS changes","startTime":"2023-10-09T17:12:49.615347045+01:00[Europe/Lisbon]","duration":1889503,"isCancelled":false}
{"reason":"Push on VFS changes","startTime":"2023-10-10T10:10:24.773108819+01:00[Europe/Lisbon]","duration":2818816,"isCancelled":false}
{"reason":"Push on VFS changes","startTime":"2023-10-10T10:46:45.072980085+01:00[Europe/Lisbon]","duration":3243176,"isCancelled":false}
{"reason":"Push on VFS changes","startTime":"2023-10-10T15:01:44.937877838+01:00[Europe/Lisbon]","duration":3348345,"isCancelled":false}
{"reason":"Push on VFS changes","startTime":"2023-10-10T15:37:58.364809979+01:00[Europe/Lisbon]","duration":2011627,"isCancelled":false}
{"reason":"Push on VFS changes","startTime":"2023-10-10T15:51:20.02200027+01:00[Europe/Lisbon]","duration":850269,"isCancelled":false}
{"reason":"Push on VFS changes","startTime":"2023-10-11T09:51:18.386602668+01:00[Europe/Lisbon]","duration":11801649,"isCancelled":false}
